BWO/__init__.py
BWO/bwo.py
BWO/constant.py
BWO/regex.py
BWO/compute/Random.py
BWO/compute/__init__.py
BlueWhite-0.1.0a0.dist-info/METADATA
BlueWhite-0.1.0a0.dist-info/WHEEL
BlueWhite-0.1.0a0.dist-info/top_level.txt
BlueWhite-0.1.0a0.dist-info/RECORD
