Metadata-Version: 2.1
Name: BlueWhite
Version: 0.1.0a0
Summary: 蓝白社数据处理与预测
Home-page: https://github.com/MoYeRanqianzhi/python-bwo
Author: MoYeRanQianZhi
Author-email: moyeranqianzhi@gmail.com
License: MIT License
Classifier: Development Status :: 3 - Alpha
Classifier: Intended Audience :: Developers
Classifier: License :: OSI Approved :: MIT License
Classifier: Programming Language :: Python
Classifier: Programming Language :: Python :: 3
Classifier: Programming Language :: Python :: 3.6
Classifier: Programming Language :: Python :: 3.7
Classifier: Programming Language :: Python :: 3.8
Classifier: Programming Language :: Python :: 3.9
Classifier: Programming Language :: Python :: 3.10
Classifier: Programming Language :: Python :: 3.11
Classifier: Programming Language :: Python :: 3.12
Requires: numpy
Requires: scipy
Requires-Python: >=3.6.0
